Workbook

Sheet Inicio
B1: ASTROS · Sistema de Información Gerencial
B2: "Aprender para crecer" · Maestros Asesores
B4: Cómo funciona | C4: Escribe solo en las columnas con encabezado AMARILLO. Las de encabezado TURQUESA se calculan solas (no las borres).
B5: 1. Leads | C5: Cada persona que escribe por IG, FB, WhatsApp o la web. Anota el canal y el código de campaña para saber qué funciona. Pon fecha de próximo seguimiento: si se vence, se pinta en rojo.
B6: 2. Alumnos | C6: Cuando un lead se inscribe, créalo aquí (el ID A001, A002... aparece solo al poner el nombre). Cambia el lead a 'Inscrito'. Aquí ves sus horas restantes y su deuda.
B7: 3. Ventas | C7: Cada paquete vendido: elige el ID del alumno y el código del producto (del Catálogo); horas y precio se llenan solos. Pon descuento si aplica.
B8: 4. Pagos | C8: Cada Yape, Plin o transferencia, con N° de operación y el ID de venta que paga. Así la deuda se actualiza sola.
B9: 5. Clases | C9: Cada clase dictada: alumno, horas, tema y link de la grabación. Descuenta horas del alumno y calcula el pago al tutor. 'Reprogramada' no descuenta.
B10: 6. Avance | C10: Notas de simulacros y prácticas. Sirve para reportes a padres y para mostrar progreso.
B11: 7. Tutores | C11: Hoy solo tú (pago 0). Cuando contrates, agrega su tarifa por hora y el sistema calcula cuánto le debes.
B12: Catálogo | C12: Tus productos y precios. Están cargados con la PROPUESTA de precios; cámbialos cuando apruebes el tarifario. El margen se calcula con el pago al tutor.
B13: Dashboard | C13: Elige el mes en la celda amarilla y verás ingresos, horas, leads, conversión y resultados por campaña.
B14: Códigos de campaña | C14: SPRINT-ULIMA, SPRINT-PUCP, REFUERZO-CEPU, MEDICINA-UPCH, VERANO-PUCP, VERANO-ULIMA, CACHIMBOS, REFERIDOS, ORGANICO. Se editan en la hoja Listas.
B15: Desde el celular | C15: Usa la app de Google Sheets. Toca una celda con flecha para elegir de la lista. Para fechas escribe dd/mm/aaaa.

Sheet Dashboard
B1: ASTROS · Panel de gestión
B3: Mes a analizar (cualquier día del mes): | C3: =TODAY()
B4: Inicio de mes | C4: =DATE(YEAR(C3),MONTH(C3),1)
B5: Fin de mes | C5: =EOMONTH(C3,0)
B7: Este mes | E7: Acumulado
B8: Ingresos cobrados | C8: =SUMIFS(Pagos!$E:$E,Pagos!$A:$A,">="&C4,Pagos!$A:$A,"<="&C5) | E8: Alumnos activos | F8: =COUNTIF(Alumnos!$M:$M,"Activo")
B9: Ventas cerradas (S/) | C9: =SUMIFS(Ventas!$I:$I,Ventas!$B:$B,">="&C4,Ventas!$B:$B,"<="&C5) | E9: Deuda por cobrar | F9: =SUMIF(Ventas!$K:$K,">0")
B10: N° de ventas | C10: =COUNTIFS(Ventas!$B:$B,">="&C4,Ventas!$B:$B,"<="&C5) | E10: Horas pendientes de dictar | F10: =SUMIF(Alumnos!$P:$P,">0")
B11: Ticket promedio | C11: =IFERROR(C9/C10,0) | E11: Leads abiertos | F11: =COUNTA(Leads!$C:$C)-1-COUNTIF(Leads!$J:$J,"Inscrito")-COUNTIF(Leads!$J:$J,"Perdido")
B12: Horas dictadas | C12: =SUMIFS(Clases!$I:$I,Clases!$A:$A,">="&C4,Clases!$A:$A,"<="&C5,Clases!$J:$J,"<>Reprogramada") | E12: Seguimientos vencidos | F12: =COUNTIF(Leads!$M:$M,">0")
B13: Pago a tutores | C13: =SUMIFS(Clases!$N:$N,Clases!$A:$A,">="&C4,Clases!$A:$A,"<="&C5) | E13: Ingresantes | F13: =COUNTIF(Alumnos!$M:$M,"Ingresó")
B14: Leads nuevos | C14: =COUNTIFS(Leads!$B:$B,">="&C4,Leads!$B:$B,"<="&C5) | E14: Ingresos totales cobrados | F14: =SUM(Pagos!$E:$E)
B15: Leads del mes ya inscritos | C15: =COUNTIFS(Leads!$B:$B,">="&C4,Leads!$B:$B,"<="&C5,Leads!$J:$J,"Inscrito")
B16: Conversión lead → alumno | C16: =IFERROR(C15/C14,0)
B18: Leads por canal (este mes) | C18: Leads | E18: Leads por universidad (este mes) | F18: Leads | G18: Inscritos
B19: Instagram | C19: =COUNTIFS(Leads!$H:$H,B19,Leads!$B:$B,">="&$C$4,Leads!$B:$B,"<="&$C$5) | E19: PUCP | F19: =COUNTIFS(Leads!$F:$F,E19,Leads!$B:$B,">="&$C$4,Leads!$B:$B,"<="&$C$5) | G19: =COUNTIFS(Leads!$F:$F,E19,Leads!$B:$B,">="&$C$4,Leads!$B:$B,"<="&$C$5,Leads!$J:$J,"Inscrito")
B20: Facebook | C20: =COUNTIFS(Leads!$H:$H,B20,Leads!$B:$B,">="&$C$4,Leads!$B:$B,"<="&$C$5) | E20: ULIMA | F20: =COUNTIFS(Leads!$F:$F,E20,Leads!$B:$B,">="&$C$4,Leads!$B:$B,"<="&$C$5) | G20: =COUNTIFS(Leads!$F:$F,E20,Leads!$B:$B,">="&$C$4,Leads!$B:$B,"<="&$C$5,Leads!$J:$J,"Inscrito")
B21: TikTok | C21: =COUNTIFS(Leads!$H:$H,B21,Leads!$B:$B,">="&$C$4,Leads!$B:$B,"<="&$C$5) | E21: UPC | F21: =COUNTIFS(Leads!$F:$F,E21,Leads!$B:$B,">="&$C$4,Leads!$B:$B,"<="&$C$5) | G21: =COUNTIFS(Leads!$F:$F,E21,Leads!$B:$B,">="&$C$4,Leads!$B:$B,"<="&$C$5,Leads!$J:$J,"Inscrito")
B22: WhatsApp | C22: =COUNTIFS(Leads!$H:$H,B22,Leads!$B:$B,">="&$C$4,Leads!$B:$B,"<="&$C$5) | E22: UPCH | F22: =COUNTIFS(Leads!$F:$F,E22,Leads!$B:$B,">="&$C$4,Leads!$B:$B,"<="&$C$5) | G22: =COUNTIFS(Leads!$F:$F,E22,Leads!$B:$B,">="&$C$4,Leads!$B:$B,"<="&$C$5,Leads!$J:$J,"Inscrito")
B23: Web | C23: =COUNTIFS(Leads!$H:$H,B23,Leads!$B:$B,">="&$C$4,Leads!$B:$B,"<="&$C$5) | E23: Otra | F23: =COUNTIFS(Leads!$F:$F,E23,Leads!$B:$B,">="&$C$4,Leads!$B:$B,"<="&$C$5) | G23: =COUNTIFS(Leads!$F:$F,E23,Leads!$B:$B,">="&$C$4,Leads!$B:$B,"<="&$C$5,Leads!$J:$J,"Inscrito")
B24: Referido | C24: =COUNTIFS(Leads!$H:$H,B24,Leads!$B:$B,">="&$C$4,Leads!$B:$B,"<="&$C$5)
B25: Colegio | C25: =COUNTIFS(Leads!$H:$H,B25,Leads!$B:$B,">="&$C$4,Leads!$B:$B,"<="&$C$5)
B26: Otro | C26: =COUNTIFS(Leads!$H:$H,B26,Leads!$B:$B,">="&$C$4,Leads!$B:$B,"<="&$C$5)
B28: Resultados por campaña (acumulado) | C28: Leads | E28: Inscritos | F28: Ventas (S/) | G28: Conversión
B29: SPRINT-ULIMA | C29: =COUNTIF(Leads!$I:$I,B29) | E29: =COUNTIFS(Leads!$I:$I,B29,Leads!$J:$J,"Inscrito") | F29: =SUMIF(Ventas!$M:$M,B29,Ventas!$I:$I) | G29: =IFERROR(E29/C29,0)
B30: SPRINT-PUCP | C30: =COUNTIF(Leads!$I:$I,B30) | E30: =COUNTIFS(Leads!$I:$I,B30,Leads!$J:$J,"Inscrito") | F30: =SUMIF(Ventas!$M:$M,B30,Ventas!$I:$I) | G30: =IFERROR(E30/C30,0)
B31: REFUERZO-CEPU | C31: =COUNTIF(Leads!$I:$I,B31) | E31: =COUNTIFS(Leads!$I:$I,B31,Leads!$J:$J,"Inscrito") | F31: =SUMIF(Ventas!$M:$M,B31,Ventas!$I:$I) | G31: =IFERROR(E31/C31,0)
B32: MEDICINA-UPCH | C32: =COUNTIF(Leads!$I:$I,B32) | E32: =COUNTIFS(Leads!$I:$I,B32,Leads!$J:$J,"Inscrito") | F32: =SUMIF(Ventas!$M:$M,B32,Ventas!$I:$I) | G32: =IFERROR(E32/C32,0)
B33: VERANO-PUCP | C33: =COUNTIF(Leads!$I:$I,B33) | E33: =COUNTIFS(Leads!$I:$I,B33,Leads!$J:$J,"Inscrito") | F33: =SUMIF(Ventas!$M:$M,B33,Ventas!$I:$I) | G33: =IFERROR(E33/C33,0)
B34: VERANO-ULIMA | C34: =COUNTIF(Leads!$I:$I,B34) | E34: =COUNTIFS(Leads!$I:$I,B34,Leads!$J:$J,"Inscrito") | F34: =SUMIF(Ventas!$M:$M,B34,Ventas!$I:$I) | G34: =IFERROR(E34/C34,0)
B35: CACHIMBOS | C35: =COUNTIF(Leads!$I:$I,B35) | E35: =COUNTIFS(Leads!$I:$I,B35,Leads!$J:$J,"Inscrito") | F35: =SUMIF(Ventas!$M:$M,B35,Ventas!$I:$I) | G35: =IFERROR(E35/C35,0)
B36: REFERIDOS | C36: =COUNTIF(Leads!$I:$I,B36) | E36: =COUNTIFS(Leads!$I:$I,B36,Leads!$J:$J,"Inscrito") | F36: =SUMIF(Ventas!$M:$M,B36,Ventas!$I:$I) | G36: =IFERROR(E36/C36,0)
B37: ORGANICO | C37: =COUNTIF(Leads!$I:$I,B37) | E37: =COUNTIFS(Leads!$I:$I,B37,Leads!$J:$J,"Inscrito") | F37: =SUMIF(Ventas!$M:$M,B37,Ventas!$I:$I) | G37: =IFERROR(E37/C37,0)

Sheet Leads
A1: ID | B1: Fecha | C1: Nombre | D1: WhatsApp | E1: Nivel | F1: Universidad objetivo | G1: Carrera / curso | H1: Canal | I1: Código campaña | J1: Estado | K1: Próximo seguimiento | L1: Notas | M1: Días sin seguimiento
A2: =IF(C2="","","L"&TEXT(ROW()-1,"000")) | M2: =IF(OR(K2="",J2="Inscrito",J2="Perdido"),"",TODAY()-K2)
A3: =IF(C3="","","L"&TEXT(ROW()-1,"000")) | M3: =IF(OR(K3="",J3="Inscrito",J3="Perdido"),"",TODAY()-K3)
A4: =IF(C4="","","L"&TEXT(ROW()-1,"000")) | M4: =IF(OR(K4="",J4="Inscrito",J4="Perdido"),"",TODAY()-K4)
A5: =IF(C5="","","L"&TEXT(ROW()-1,"000")) | M5: =IF(OR(K5="",J5="Inscrito",J5="Perdido"),"",TODAY()-K5)
A6: =IF(C6="","","L"&TEXT(ROW()-1,"000")) | M6: =IF(OR(K6="",J6="Inscrito",J6="Perdido"),"",TODAY()-K6)
A7: =IF(C7="","","L"&TEXT(ROW()-1,"000")) | M7: =IF(OR(K7="",J7="Inscrito",J7="Perdido"),"",TODAY()-K7)
A8: =IF(C8="","","L"&TEXT(ROW()-1,"000")) | M8: =IF(OR(K8="",J8="Inscrito",J8="Perdido"),"",TODAY()-K8)
A9: =IF(C9="","","L"&TEXT(ROW()-1,"000")) | M9: =IF(OR(K9="",J9="Inscrito",J9="Perdido"),"",TODAY()-K9)
A10: =IF(C10="","","L"&TEXT(ROW()-1,"000")) | M10: =IF(OR(K10="",J10="Inscrito",J10="Perdido"),"",TODAY()-K10)
A11: =IF(C11="","","L"&TEXT(ROW()-1,"000")) | M11: =IF(OR(K11="",J11="Inscrito",J11="Perdido"),"",TODAY()-K11)
A12: =IF(C12="","","L"&TEXT(ROW()-1,"000")) | M12: =IF(OR(K12="",J12="Inscrito",J12="Perdido"),"",TODAY()-K12)
A13: =IF(C13="","","L"&TEXT(ROW()-1,"000")) | M13: =IF(OR(K13="",J13="Inscrito",J13="Perdido"),"",TODAY()-K13)
... A501: =IF(C501="","","L"&TEXT(ROW()-1,"000")) | M501: =IF(OR(K501="",J501="Inscrito",J501="Perdido"),"",TODAY()-K501)

Sheet Alumnos
A1: ID | B1: Nombre | C1: WhatsApp | D1: Correo | E1: Nivel | F1: Colegio / Universidad actual | G1: Universidad objetivo | H1: Carrera | I1: Fecha examen | J1: Apoderado | K1: WhatsApp apoderado | L1: ID lead | M1: Estado | N1: Horas compradas | O1: Horas dictadas | P1: Horas restantes | Q1: Total vendido (S/) | R1: Total pagado (S/) | S1: Deuda (S/)
A2: =IF(B2="","","A"&TEXT(ROW()-1,"000")) | N2: =IF(A2="","",SUMIFS(Ventas!$F:$F,Ventas!$C:$C,A2)) | O2: =IF(A2="","",SUMIFS(Clases!$I:$I,Clases!$C:$C,A2,Clases!$J:$J,"<>Reprogramada")) | P2: =IF(A2="","",N2-O2) | Q2: =IF(A2="","",SUMIFS(Ventas!$I:$I,Ventas!$C:$C,A2)) | R2: =IF(A2="","",SUMIFS(Pagos!$E:$E,Pagos!$C:$C,A2)) | S2: =IF(A2="","",Q2-R2)
A3: =IF(B3="","","A"&TEXT(ROW()-1,"000")) | N3: =IF(A3="","",SUMIFS(Ventas!$F:$F,Ventas!$C:$C,A3)) | O3: =IF(A3="","",SUMIFS(Clases!$I:$I,Clases!$C:$C,A3,Clases!$J:$J,"<>Reprogramada")) | P3: =IF(A3="","",N3-O3) | Q3: =IF(A3="","",SUMIFS(Ventas!$I:$I,Ventas!$C:$C,A3)) | R3: =IF(A3="","",SUMIFS(Pagos!$E:$E,Pagos!$C:$C,A3)) | S3: =IF(A3="","",Q3-R3)
A4: =IF(B4="","","A"&TEXT(ROW()-1,"000")) | N4: =IF(A4="","",SUMIFS(Ventas!$F:$F,Ventas!$C:$C,A4)) | O4: =IF(A4="","",SUMIFS(Clases!$I:$I,Clases!$C:$C,A4,Clases!$J:$J,"<>Reprogramada")) | P4: =IF(A4="","",N4-O4) | Q4: =IF(A4="","",SUMIFS(Ventas!$I:$I,Ventas!$C:$C,A4)) | R4: =IF(A4="","",SUMIFS(Pagos!$E:$E,Pagos!$C:$C,A4)) | S4: =IF(A4="","",Q4-R4)
A5: =IF(B5="","","A"&TEXT(ROW()-1,"000")) | N5: =IF(A5="","",SUMIFS(Ventas!$F:$F,Ventas!$C:$C,A5)) | O5: =IF(A5="","",SUMIFS(Clases!$I:$I,Clases!$C:$C,A5,Clases!$J:$J,"<>Reprogramada")) | P5: =IF(A5="","",N5-O5) | Q5: =IF(A5="","",SUMIFS(Ventas!$I:$I,Ventas!$C:$C,A5)) | R5: =IF(A5="","",SUMIFS(Pagos!$E:$E,Pagos!$C:$C,A5)) | S5: =IF(A5="","",Q5-R5)
A6: =IF(B6="","","A"&TEXT(ROW()-1,"000")) | N6: =IF(A6="","",SUMIFS(Ventas!$F:$F,Ventas!$C:$C,A6)) | O6: =IF(A6="","",SUMIFS(Clases!$I:$I,Clases!$C:$C,A6,Clases!$J:$J,"<>Reprogramada")) | P6: =IF(A6="","",N6-O6) | Q6: =IF(A6="","",SUMIFS(Ventas!$I:$I,Ventas!$C:$C,A6)) | R6: =IF(A6="","",SUMIFS(Pagos!$E:$E,Pagos!$C:$C,A6)) | S6: =IF(A6="","",Q6-R6)
A7: =IF(B7="","","A"&TEXT(ROW()-1,"000")) | N7: =IF(A7="","",SUMIFS(Ventas!$F:$F,Ventas!$C:$C,A7)) | O7: =IF(A7="","",SUMIFS(Clases!$I:$I,Clases!$C:$C,A7,Clases!$J:$J,"<>Reprogramada")) | P7: =IF(A7="","",N7-O7) | Q7: =IF(A7="","",SUMIFS(Ventas!$I:$I,Ventas!$C:$C,A7)) | R7: =IF(A7="","",SUMIFS(Pagos!$E:$E,Pagos!$C:$C,A7)) | S7: =IF(A7="","",Q7-R7)
A8: =IF(B8="","","A"&TEXT(ROW()-1,"000")) | N8: =IF(A8="","",SUMIFS(Ventas!$F:$F,Ventas!$C:$C,A8)) | O8: =IF(A8="","",SUMIFS(Clases!$I:$I,Clases!$C:$C,A8,Clases!$J:$J,"<>Reprogramada")) | P8: =IF(A8="","",N8-O8) | Q8: =IF(A8="","",SUMIFS(Ventas!$I:$I,Ventas!$C:$C,A8)) | R8: =IF(A8="","",SUMIFS(Pagos!$E:$E,Pagos!$C:$C,A8)) | S8: =IF(A8="","",Q8-R8)
A9: =IF(B9="","","A"&TEXT(ROW()-1,"000")) | N9: =IF(A9="","",SUMIFS(Ventas!$F:$F,Ventas!$C:$C,A9)) | O9: =IF(A9="","",SUMIFS(Clases!$I:$I,Clases!$C:$C,A9,Clases!$J:$J,"<>Reprogramada")) | P9: =IF(A9="","",N9-O9) | Q9: =IF(A9="","",SUMIFS(Ventas!$I:$I,Ventas!$C:$C,A9)) | R9: =IF(A9="","",SUMIFS(Pagos!$E:$E,Pagos!$C:$C,A9)) | S9: =IF(A9="","",Q9-R9)
A10: =IF(B10="","","A"&TEXT(ROW()-1,"000")) | N10: =IF(A10="","",SUMIFS(Ventas!$F:$F,Ventas!$C:$C,A10)) | O10: =IF(A10="","",SUMIFS(Clases!$I:$I,Clases!$C:$C,A10,Clases!$J:$J,"<>Reprogramada")) | P10: =IF(A10="","",N10-O10) | Q10: =IF(A10="","",SUMIFS(Ventas!$I:$I,Ventas!$C:$C,A10)) | R10: =IF(A10="","",SUMIFS(Pagos!$E:$E,Pagos!$C:$C,A10)) | S10: =IF(A10="","",Q10-R10)
A11: =IF(B11="","","A"&TEXT(ROW()-1,"000")) | N11: =IF(A11="","",SUMIFS(Ventas!$F:$F,Ventas!$C:$C,A11)) | O11: =IF(A11="","",SUMIFS(Clases!$I:$I,Clases!$C:$C,A11,Clases!$J:$J,"<>Reprogramada")) | P11: =IF(A11="","",N11-O11) | Q11: =IF(A11="","",SUMIFS(Ventas!$I:$I,Ventas!$C:$C,A11)) | R11: =IF(A11="","",SUMIFS(Pagos!$E:$E,Pagos!$C:$C,A11)) | S11: =IF(A11="","",Q11-R11)
A12: =IF(B12="","","A"&TEXT(ROW()-1,"000")) | N12: =IF(A12="","",SUMIFS(Ventas!$F:$F,Ventas!$C:$C,A12)) | O12: =IF(A12="","",SUMIFS(Clases!$I:$I,Clases!$C:$C,A12,Clases!$J:$J,"<>Reprogramada")) | P12: =IF(A12="","",N12-O12) | Q12: =IF(A12="","",SUMIFS(Ventas!$I:$I,Ventas!$C:$C,A12)) | R12: =IF(A12="","",SUMIFS(Pagos!$E:$E,Pagos!$C:$C,A12)) | S12: =IF(A12="","",Q12-R12)
A13: =IF(B13="","","A"&TEXT(ROW()-1,"000")) | N13: =IF(A13="","",SUMIFS(Ventas!$F:$F,Ventas!$C:$C,A13)) | O13: =IF(A13="","",SUMIFS(Clases!$I:$I,Clases!$C:$C,A13,Clases!$J:$J,"<>Reprogramada")) | P13: =IF(A13="","",N13-O13) | Q13: =IF(A13="","",SUMIFS(Ventas!$I:$I,Ventas!$C:$C,A13)) | R13: =IF(A13="","",SUMIFS(Pagos!$E:$E,Pagos!$C:$C,A13)) | S13: =IF(A13="","",Q13-R13)
... A501: =IF(B501="","","A"&TEXT(ROW()-1,"000")) | N501: =IF(A501="","",SUMIFS(Ventas!$F:$F,Ventas!$C:$C,A501)) | O501: =IF(A501="","",SUMIFS(Clases!$I:$I,Clases!$C:$C,A501,Clases!$J:$J,"<>Reprogramada")) | P501: =IF(A501="","",N501-O501) | Q501: =IF(A501="","",SUMIFS(Ventas!$I:$I,Ventas!$C:$C,A501)) | R501: =IF(A501="","",SUMIFS(Pagos!$E:$E,Pagos!$C:$C,A501)) | S501: =IF(A501="","",Q501-R501)

Sheet Ventas
A1: ID venta | B1: Fecha | C1: ID alumno | D1: Alumno | E1: Código producto | F1: Horas | G1: Precio lista (S/) | H1: Descuento (S/) | I1: Total (S/) | J1: Pagado (S/) | K1: Saldo (S/) | L1: Vence (60 días) | M1: Código campaña | N1: Notas
A2: =IF(C2="","","V"&TEXT(ROW()-1,"000")) | D2: =IFERROR(VLOOKUP(C2,Alumnos!$A:$B,2,FALSE),"") | F2: =IFERROR(VLOOKUP(E2,Catalogo!$A$2:$H$60,4,FALSE),"") | G2: =IFERROR(VLOOKUP(E2,Catalogo!$A$2:$H$60,5,FALSE),"") | I2: =IF(G2="","",G2-H2) | J2: =IF(A2="","",SUMIFS(Pagos!$E:$E,Pagos!$D:$D,A2)) | K2: =IF(A2="","",I2-J2) | L2: =IF(B2="","",B2+60)
A3: =IF(C3="","","V"&TEXT(ROW()-1,"000")) | D3: =IFERROR(VLOOKUP(C3,Alumnos!$A:$B,2,FALSE),"") | F3: =IFERROR(VLOOKUP(E3,Catalogo!$A$2:$H$60,4,FALSE),"") | G3: =IFERROR(VLOOKUP(E3,Catalogo!$A$2:$H$60,5,FALSE),"") | I3: =IF(G3="","",G3-H3) | J3: =IF(A3="","",SUMIFS(Pagos!$E:$E,Pagos!$D:$D,A3)) | K3: =IF(A3="","",I3-J3) | L3: =IF(B3="","",B3+60)
A4: =IF(C4="","","V"&TEXT(ROW()-1,"000")) | D4: =IFERROR(VLOOKUP(C4,Alumnos!$A:$B,2,FALSE),"") | F4: =IFERROR(VLOOKUP(E4,Catalogo!$A$2:$H$60,4,FALSE),"") | G4: =IFERROR(VLOOKUP(E4,Catalogo!$A$2:$H$60,5,FALSE),"") | I4: =IF(G4="","",G4-H4) | J4: =IF(A4="","",SUMIFS(Pagos!$E:$E,Pagos!$D:$D,A4)) | K4: =IF(A4="","",I4-J4) | L4: =IF(B4="","",B4+60)
A5: =IF(C5="","","V"&TEXT(ROW()-1,"000")) | D5: =IFERROR(VLOOKUP(C5,Alumnos!$A:$B,2,FALSE),"") | F5: =IFERROR(VLOOKUP(E5,Catalogo!$A$2:$H$60,4,FALSE),"") | G5: =IFERROR(VLOOKUP(E5,Catalogo!$A$2:$H$60,5,FALSE),"") | I5: =IF(G5="","",G5-H5) | J5: =IF(A5="","",SUMIFS(Pagos!$E:$E,Pagos!$D:$D,A5)) | K5: =IF(A5="","",I5-J5) | L5: =IF(B5="","",B5+60)
A6: =IF(C6="","","V"&TEXT(ROW()-1,"000")) | D6: =IFERROR(VLOOKUP(C6,Alumnos!$A:$B,2,FALSE),"") | F6: =IFERROR(VLOOKUP(E6,Catalogo!$A$2:$H$60,4,FALSE),"") | G6: =IFERROR(VLOOKUP(E6,Catalogo!$A$2:$H$60,5,FALSE),"") | I6: =IF(G6="","",G6-H6) | J6: =IF(A6="","",SUMIFS(Pagos!$E:$E,Pagos!$D:$D,A6)) | K6: =IF(A6="","",I6-J6) | L6: =IF(B6="","",B6+60)
A7: =IF(C7="","","V"&TEXT(ROW()-1,"000")) | D7: =IFERROR(VLOOKUP(C7,Alumnos!$A:$B,2,FALSE),"") | F7: =IFERROR(VLOOKUP(E7,Catalogo!$A$2:$H$60,4,FALSE),"") | G7: =IFERROR(VLOOKUP(E7,Catalogo!$A$2:$H$60,5,FALSE),"") | I7: =IF(G7="","",G7-H7) | J7: =IF(A7="","",SUMIFS(Pagos!$E:$E,Pagos!$D:$D,A7)) | K7: =IF(A7="","",I7-J7) | L7: =IF(B7="","",B7+60)
A8: =IF(C8="","","V"&TEXT(ROW()-1,"000")) | D8: =IFERROR(VLOOKUP(C8,Alumnos!$A:$B,2,FALSE),"") | F8: =IFERROR(VLOOKUP(E8,Catalogo!$A$2:$H$60,4,FALSE),"") | G8: =IFERROR(VLOOKUP(E8,Catalogo!$A$2:$H$60,5,FALSE),"") | I8: =IF(G8="","",G8-H8) | J8: =IF(A8="","",SUMIFS(Pagos!$E:$E,Pagos!$D:$D,A8)) | K8: =IF(A8="","",I8-J8) | L8: =IF(B8="","",B8+60)
A9: =IF(C9="","","V"&TEXT(ROW()-1,"000")) | D9: =IFERROR(VLOOKUP(C9,Alumnos!$A:$B,2,FALSE),"") | F9: =IFERROR(VLOOKUP(E9,Catalogo!$A$2:$H$60,4,FALSE),"") | G9: =IFERROR(VLOOKUP(E9,Catalogo!$A$2:$H$60,5,FALSE),"") | I9: =IF(G9="","",G9-H9) | J9: =IF(A9="","",SUMIFS(Pagos!$E:$E,Pagos!$D:$D,A9)) | K9: =IF(A9="","",I9-J9) | L9: =IF(B9="","",B9+60)
A10: =IF(C10="","","V"&TEXT(ROW()-1,"000")) | D10: =IFERROR(VLOOKUP(C10,Alumnos!$A:$B,2,FALSE),"") | F10: =IFERROR(VLOOKUP(E10,Catalogo!$A$2:$H$60,4,FALSE),"") | G10: =IFERROR(VLOOKUP(E10,Catalogo!$A$2:$H$60,5,FALSE),"") | I10: =IF(G10="","",G10-H10) | J10: =IF(A10="","",SUMIFS(Pagos!$E:$E,Pagos!$D:$D,A10)) | K10: =IF(A10="","",I10-J10) | L10: =IF(B10="","",B10+60)
A11: =IF(C11="","","V"&TEXT(ROW()-1,"000")) | D11: =IFERROR(VLOOKUP(C11,Alumnos!$A:$B,2,FALSE),"") | F11: =IFERROR(VLOOKUP(E11,Catalogo!$A$2:$H$60,4,FALSE),"") | G11: =IFERROR(VLOOKUP(E11,Catalogo!$A$2:$H$60,5,FALSE),"") | I11: =IF(G11="","",G11-H11) | J11: =IF(A11="","",SUMIFS(Pagos!$E:$E,Pagos!$D:$D,A11)) | K11: =IF(A11="","",I11-J11) | L11: =IF(B11="","",B11+60)
A12: =IF(C12="","","V"&TEXT(ROW()-1,"000")) | D12: =IFERROR(VLOOKUP(C12,Alumnos!$A:$B,2,FALSE),"") | F12: =IFERROR(VLOOKUP(E12,Catalogo!$A$2:$H$60,4,FALSE),"") | G12: =IFERROR(VLOOKUP(E12,Catalogo!$A$2:$H$60,5,FALSE),"") | I12: =IF(G12="","",G12-H12) | J12: =IF(A12="","",SUMIFS(Pagos!$E:$E,Pagos!$D:$D,A12)) | K12: =IF(A12="","",I12-J12) | L12: =IF(B12="","",B12+60)
A13: =IF(C13="","","V"&TEXT(ROW()-1,"000")) | D13: =IFERROR(VLOOKUP(C13,Alumnos!$A:$B,2,FALSE),"") | F13: =IFERROR(VLOOKUP(E13,Catalogo!$A$2:$H$60,4,FALSE),"") | G13: =IFERROR(VLOOKUP(E13,Catalogo!$A$2:$H$60,5,FALSE),"") | I13: =IF(G13="","",G13-H13) | J13: =IF(A13="","",SUMIFS(Pagos!$E:$E,Pagos!$D:$D,A13)) | K13: =IF(A13="","",I13-J13) | L13: =IF(B13="","",B13+60)
... A501: =IF(C501="","","V"&TEXT(ROW()-1,"000")) | D501: =IFERROR(VLOOKUP(C501,Alumnos!$A:$B,2,FALSE),"") | F501: =IFERROR(VLOOKUP(E501,Catalogo!$A$2:$H$60,4,FALSE),"") | G501: =IFERROR(VLOOKUP(E501,Catalogo!$A$2:$H$60,5,FALSE),"") | I501: =IF(G501="","",G501-H501) | J501: =IF(A501="","",SUMIFS(Pagos!$E:$E,Pagos!$D:$D,A501)) | K501: =IF(A501="","",I501-J501) | L501: =IF(B501="","",B501+60)

Sheet Pagos
A1: Fecha | B1: N° operación | C1: ID alumno | D1: ID venta | E1: Monto (S/) | F1: Medio | G1: ¿Comprobante recibido? | H1: Alumno | I1: Notas
H2: =IFERROR(VLOOKUP(C2,Alumnos!$A:$B,2,FALSE),"")
H3: =IFERROR(VLOOKUP(C3,Alumnos!$A:$B,2,FALSE),"")
H4: =IFERROR(VLOOKUP(C4,Alumnos!$A:$B,2,FALSE),"")
H5: =IFERROR(VLOOKUP(C5,Alumnos!$A:$B,2,FALSE),"")
H6: =IFERROR(VLOOKUP(C6,Alumnos!$A:$B,2,FALSE),"")
H7: =IFERROR(VLOOKUP(C7,Alumnos!$A:$B,2,FALSE),"")
H8: =IFERROR(VLOOKUP(C8,Alumnos!$A:$B,2,FALSE),"")
H9: =IFERROR(VLOOKUP(C9,Alumnos!$A:$B,2,FALSE),"")
H10: =IFERROR(VLOOKUP(C10,Alumnos!$A:$B,2,FALSE),"")
H11: =IFERROR(VLOOKUP(C11,Alumnos!$A:$B,2,FALSE),"")
H12: =IFERROR(VLOOKUP(C12,Alumnos!$A:$B,2,FALSE),"")
H13: =IFERROR(VLOOKUP(C13,Alumnos!$A:$B,2,FALSE),"")
... H501: =IFERROR(VLOOKUP(C501,Alumnos!$A:$B,2,FALSE),"")

Sheet Clases
A1: Fecha | B1: Hora inicio | C1: ID alumno | D1: Alumno | E1: ID venta | F1: Tutor | G1: Curso | H1: Tema | I1: Horas | J1: Asistencia | K1: Modalidad | L1: Link grabación (Drive) | M1: Tarea / próximo paso | N1: Pago tutor (S/)
D2: =IFERROR(VLOOKUP(C2,Alumnos!$A:$B,2,FALSE),"") | N2: =IF(OR(F2="",I2="",J2="Reprogramada"),"",I2*IFERROR(VLOOKUP(F2,Tutores!$A:$F,6,FALSE),0))
D3: =IFERROR(VLOOKUP(C3,Alumnos!$A:$B,2,FALSE),"") | N3: =IF(OR(F3="",I3="",J3="Reprogramada"),"",I3*IFERROR(VLOOKUP(F3,Tutores!$A:$F,6,FALSE),0))
D4: =IFERROR(VLOOKUP(C4,Alumnos!$A:$B,2,FALSE),"") | N4: =IF(OR(F4="",I4="",J4="Reprogramada"),"",I4*IFERROR(VLOOKUP(F4,Tutores!$A:$F,6,FALSE),0))
D5: =IFERROR(VLOOKUP(C5,Alumnos!$A:$B,2,FALSE),"") | N5: =IF(OR(F5="",I5="",J5="Reprogramada"),"",I5*IFERROR(VLOOKUP(F5,Tutores!$A:$F,6,FALSE),0))
D6: =IFERROR(VLOOKUP(C6,Alumnos!$A:$B,2,FALSE),"") | N6: =IF(OR(F6="",I6="",J6="Reprogramada"),"",I6*IFERROR(VLOOKUP(F6,Tutores!$A:$F,6,FALSE),0))
D7: =IFERROR(VLOOKUP(C7,Alumnos!$A:$B,2,FALSE),"") | N7: =IF(OR(F7="",I7="",J7="Reprogramada"),"",I7*IFERROR(VLOOKUP(F7,Tutores!$A:$F,6,FALSE),0))
D8: =IFERROR(VLOOKUP(C8,Alumnos!$A:$B,2,FALSE),"") | N8: =IF(OR(F8="",I8="",J8="Reprogramada"),"",I8*IFERROR(VLOOKUP(F8,Tutores!$A:$F,6,FALSE),0))
D9: =IFERROR(VLOOKUP(C9,Alumnos!$A:$B,2,FALSE),"") | N9: =IF(OR(F9="",I9="",J9="Reprogramada"),"",I9*IFERROR(VLOOKUP(F9,Tutores!$A:$F,6,FALSE),0))
D10: =IFERROR(VLOOKUP(C10,Alumnos!$A:$B,2,FALSE),"") | N10: =IF(OR(F10="",I10="",J10="Reprogramada"),"",I10*IFERROR(VLOOKUP(F10,Tutores!$A:$F,6,FALSE),0))
D11: =IFERROR(VLOOKUP(C11,Alumnos!$A:$B,2,FALSE),"") | N11: =IF(OR(F11="",I11="",J11="Reprogramada"),"",I11*IFERROR(VLOOKUP(F11,Tutores!$A:$F,6,FALSE),0))
D12: =IFERROR(VLOOKUP(C12,Alumnos!$A:$B,2,FALSE),"") | N12: =IF(OR(F12="",I12="",J12="Reprogramada"),"",I12*IFERROR(VLOOKUP(F12,Tutores!$A:$F,6,FALSE),0))
D13: =IFERROR(VLOOKUP(C13,Alumnos!$A:$B,2,FALSE),"") | N13: =IF(OR(F13="",I13="",J13="Reprogramada"),"",I13*IFERROR(VLOOKUP(F13,Tutores!$A:$F,6,FALSE),0))
... D501: =IFERROR(VLOOKUP(C501,Alumnos!$A:$B,2,FALSE),"") | N501: =IF(OR(F501="",I501="",J501="Reprogramada"),"",I501*IFERROR(VLOOKUP(F501,Tutores!$A:$F,6,FALSE),0))

Sheet Avance
A1: Fecha | B1: ID alumno | C1: Alumno | D1: Universidad | E1: Tipo (simulacro / práctica / nota univ.) | F1: Área / curso | G1: Puntaje | H1: Puntaje máximo | I1: % logro | J1: Temas débiles | K1: Comentario para el alumno/padre
C2: =IFERROR(VLOOKUP(B2,Alumnos!$A:$B,2,FALSE),"") | I2: =IF(OR(G2="",H2=""),"",G2/H2)
C3: =IFERROR(VLOOKUP(B3,Alumnos!$A:$B,2,FALSE),"") | I3: =IF(OR(G3="",H3=""),"",G3/H3)
C4: =IFERROR(VLOOKUP(B4,Alumnos!$A:$B,2,FALSE),"") | I4: =IF(OR(G4="",H4=""),"",G4/H4)
C5: =IFERROR(VLOOKUP(B5,Alumnos!$A:$B,2,FALSE),"") | I5: =IF(OR(G5="",H5=""),"",G5/H5)
C6: =IFERROR(VLOOKUP(B6,Alumnos!$A:$B,2,FALSE),"") | I6: =IF(OR(G6="",H6=""),"",G6/H6)
C7: =IFERROR(VLOOKUP(B7,Alumnos!$A:$B,2,FALSE),"") | I7: =IF(OR(G7="",H7=""),"",G7/H7)
C8: =IFERROR(VLOOKUP(B8,Alumnos!$A:$B,2,FALSE),"") | I8: =IF(OR(G8="",H8=""),"",G8/H8)
C9: =IFERROR(VLOOKUP(B9,Alumnos!$A:$B,2,FALSE),"") | I9: =IF(OR(G9="",H9=""),"",G9/H9)
C10: =IFERROR(VLOOKUP(B10,Alumnos!$A:$B,2,FALSE),"") | I10: =IF(OR(G10="",H10=""),"",G10/H10)
C11: =IFERROR(VLOOKUP(B11,Alumnos!$A:$B,2,FALSE),"") | I11: =IF(OR(G11="",H11=""),"",G11/H11)
C12: =IFERROR(VLOOKUP(B12,Alumnos!$A:$B,2,FALSE),"") | I12: =IF(OR(G12="",H12=""),"",G12/H12)
C13: =IFERROR(VLOOKUP(B13,Alumnos!$A:$B,2,FALSE),"") | I13: =IF(OR(G13="",H13=""),"",G13/H13)
... C501: =IFERROR(VLOOKUP(B501,Alumnos!$A:$B,2,FALSE),"") | I501: =IF(OR(G501="",H501=""),"",G501/H501)

Sheet Tutores
A1: Nombre | B1: WhatsApp | C1: Cursos que dicta | D1: Niveles | E1: Disponibilidad | F1: Pago por hora (S/) | G1: Estado | H1: Horas dictadas | I1: Por pagar (S/)
A2: Martini | C2: Todos | D2: Todos | F2: 0 | G2: Activo | H2: =IF(A2="","",SUMIFS(Clases!$I:$I,Clases!$F:$F,A2,Clases!$J:$J,"<>Reprogramada")) | I2: =IF(A2="","",SUMIFS(Clases!$N:$N,Clases!$F:$F,A2))
H3: =IF(A3="","",SUMIFS(Clases!$I:$I,Clases!$F:$F,A3,Clases!$J:$J,"<>Reprogramada")) | I3: =IF(A3="","",SUMIFS(Clases!$N:$N,Clases!$F:$F,A3))
H4: =IF(A4="","",SUMIFS(Clases!$I:$I,Clases!$F:$F,A4,Clases!$J:$J,"<>Reprogramada")) | I4: =IF(A4="","",SUMIFS(Clases!$N:$N,Clases!$F:$F,A4))
H5: =IF(A5="","",SUMIFS(Clases!$I:$I,Clases!$F:$F,A5,Clases!$J:$J,"<>Reprogramada")) | I5: =IF(A5="","",SUMIFS(Clases!$N:$N,Clases!$F:$F,A5))
H6: =IF(A6="","",SUMIFS(Clases!$I:$I,Clases!$F:$F,A6,Clases!$J:$J,"<>Reprogramada")) | I6: =IF(A6="","",SUMIFS(Clases!$N:$N,Clases!$F:$F,A6))
H7: =IF(A7="","",SUMIFS(Clases!$I:$I,Clases!$F:$F,A7,Clases!$J:$J,"<>Reprogramada")) | I7: =IF(A7="","",SUMIFS(Clases!$N:$N,Clases!$F:$F,A7))
H8: =IF(A8="","",SUMIFS(Clases!$I:$I,Clases!$F:$F,A8,Clases!$J:$J,"<>Reprogramada")) | I8: =IF(A8="","",SUMIFS(Clases!$N:$N,Clases!$F:$F,A8))
H9: =IF(A9="","",SUMIFS(Clases!$I:$I,Clases!$F:$F,A9,Clases!$J:$J,"<>Reprogramada")) | I9: =IF(A9="","",SUMIFS(Clases!$N:$N,Clases!$F:$F,A9))
H10: =IF(A10="","",SUMIFS(Clases!$I:$I,Clases!$F:$F,A10,Clases!$J:$J,"<>Reprogramada")) | I10: =IF(A10="","",SUMIFS(Clases!$N:$N,Clases!$F:$F,A10))
H11: =IF(A11="","",SUMIFS(Clases!$I:$I,Clases!$F:$F,A11,Clases!$J:$J,"<>Reprogramada")) | I11: =IF(A11="","",SUMIFS(Clases!$N:$N,Clases!$F:$F,A11))
H12: =IF(A12="","",SUMIFS(Clases!$I:$I,Clases!$F:$F,A12,Clases!$J:$J,"<>Reprogramada")) | I12: =IF(A12="","",SUMIFS(Clases!$N:$N,Clases!$F:$F,A12))
H13: =IF(A13="","",SUMIFS(Clases!$I:$I,Clases!$F:$F,A13,Clases!$J:$J,"<>Reprogramada")) | I13: =IF(A13="","",SUMIFS(Clases!$N:$N,Clases!$F:$F,A13))
H14: =IF(A14="","",SUMIFS(Clases!$I:$I,Clases!$F:$F,A14,Clases!$J:$J,"<>Reprogramada")) | I14: =IF(A14="","",SUMIFS(Clases!$N:$N,Clases!$F:$F,A14))
... H50: =IF(A50="","",SUMIFS(Clases!$I:$I,Clases!$F:$F,A50,Clases!$J:$J,"<>Reprogramada")) | I50: =IF(A50="","",SUMIFS(Clases!$N:$N,Clases!$F:$F,A50))

Sheet Catalogo
A1: Código | B1: Nivel | C1: Producto | D1: Horas | E1: Precio (S/) | F1: S/ por hora | G1: Pago tutor por hora (S/) | H1: Margen % | I1: Estado del precio
A2: ESC-1 | B2: Escolar | C2: Hora suelta | D2: 1 | E2: 40 | F2: =IFERROR(E2/D2,"") | G2: 20 | H2: =IFERROR((F2-G2)/F2,"") | I2: Propuesta: edítalo al aprobar precios
A3: ESC-8 | B3: Escolar | C3: Pack 8 h (1 mes, 2 h/sem) | D3: 8 | E3: 280 | F3: =IFERROR(E3/D3,"") | G3: 20 | H3: =IFERROR((F3-G3)/F3,"") | I3: Propuesta: edítalo al aprobar precios
A4: ESC-16 | B4: Escolar | C4: Pack 16 h (1 mes, 4 h/sem) | D4: 16 | E4: 512 | F4: =IFERROR(E4/D4,"") | G4: 20 | H4: =IFERROR((F4-G4)/F4,"") | I4: Propuesta: edítalo al aprobar precios
A5: PRE-1 | B5: Preuniversitario | C5: Hora suelta | D5: 1 | E5: 50 | F5: =IFERROR(E5/D5,"") | G5: 25 | H5: =IFERROR((F5-G5)/F5,"") | I5: Propuesta: edítalo al aprobar precios
A6: PRE-12 | B6: Preuniversitario | C6: Pack 12 h | D6: 12 | E6: 540 | F6: =IFERROR(E6/D6,"") | G6: 25 | H6: =IFERROR((F6-G6)/F6,"") | I6: Propuesta: edítalo al aprobar precios
A7: PRE-24 | B7: Preuniversitario | C7: Programa mensual 24 h | D7: 24 | E7: 960 | F7: =IFERROR(E7/D7,"") | G7: 25 | H7: =IFERROR((F7-G7)/F7,"") | I7: Propuesta: edítalo al aprobar precios
A8: UNI-1 | B8: Universitario | C8: Hora suelta | D8: 1 | E8: 60 | F8: =IFERROR(E8/D8,"") | G8: 30 | H8: =IFERROR((F8-G8)/F8,"") | I8: Propuesta: edítalo al aprobar precios
A9: UNI-PC | B9: Universitario | C9: Práctica (4 h) | D9: 4 | E9: 220 | F9: =IFERROR(E9/D9,"") | G9: 30 | H9: =IFERROR((F9-G9)/F9,"") | I9: Propuesta: edítalo al aprobar precios
A10: UNI-EX | B10: Universitario | C10: Examen (8 h) | D10: 8 | E10: 400 | F10: =IFERROR(E10/D10,"") | G10: 30 | H10: =IFERROR((F10-G10)/F10,"") | I10: Propuesta: edítalo al aprobar precios
A11: UNI-MC | B11: Universitario | C11: Medio ciclo (2 EP + 1 EX) | D11: 16 | E11: 760 | F11: =IFERROR(E11/D11,"") | G11: 30 | H11: =IFERROR((F11-G11)/F11,"") | I11: Propuesta: edítalo al aprobar precios
A12: UNI-CC | B12: Universitario | C12: Ciclo completo (4 EP + 2 EX) | D12: 32 | E12: 1440 | F12: =IFERROR(E12/D12,"") | G12: 30 | H12: =IFERROR((F12-G12)/F12,"") | I12: Propuesta: edítalo al aprobar precios
A13: TALLER | B13: Universitario | C13: Taller intensivo pre-examen (por alumno) | D13: 3 | E13: 49 | F13: =IFERROR(E13/D13,"") | G13: 30 | H13: =IFERROR((F13-G13)/F13,"") | I13: Propuesta: edítalo al aprobar precios
A14: DIAG | B14: Preuniversitario | C14: Clase diagnóstica gratis (45 min) | D14: 0.75 | E14: 0 | F14: =IFERROR(E14/D14,"") | G14: 0 | H14: =IFERROR((F14-G14)/F14,"") | I14: Propuesta: edítalo al aprobar precios

Sheet Listas
A1: Nivel | B1: Universidad | C1: Canal | D1: EstadoLead | E1: Modalidad | F1: MedioPago | G1: EstadoAlumno | H1: Asistencia | I1: Campaña
A2: Escolar | B2: PUCP | C2: Instagram | D2: Nuevo | E2: Virtual | F2: Yape | G2: Activo | H2: Asistió | I2: SPRINT-ULIMA
A3: Preuniversitario | B3: ULIMA | C3: Facebook | D3: Contactado | E3: Presencial | F3: Plin | G3: Pausado | H3: Faltó (se descuenta) | I3: SPRINT-PUCP
A4: Universitario | B4: UPC | C4: TikTok | D4: Diagnóstico agendado | E4: A domicilio | F4: BCP | G4: Terminó | H4: Reprogramada | I4: REFUERZO-CEPU
B5: UPCH | C5: WhatsApp | D5: Diagnóstico hecho | F5: BBVA | G5: Ingresó | I5: MEDICINA-UPCH
B6: Otra | C6: Web | D6: Propuesta enviada | F6: Interbank | I6: VERANO-PUCP
B7: No aplica | C7: Referido | D7: Inscrito | F7: Scotiabank | I7: VERANO-ULIMA
C8: Colegio | D8: Perdido | F8: Efectivo | I8: CACHIMBOS
C9: Otro | I9: REFERIDOS
I10: ORGANICO
