Workbook

Sheet Inicio
A1: ASTROS · Plan de campañas oct 2026 – abr 2027
A3: Qué es | B3: El plan ejecutable de marketing: qué publicar cada semana, con qué texto, para qué campaña y con cuánto presupuesto. Se apoya en el cronograma de admisión (fechas y metas) y en el tarifario aprobado.
A4: Campañas | B4: Una fila por campaña: objetivo, público, oferta con precios, gancho, canales, presupuesto y metas.
A5: Calendario | B5: Semana a semana: 3 publicaciones + 1 difusión por WhatsApp. Cambia la columna Estado a 'Publicado' cuando lo subas.
A6: WhatsApp | B6: Guiones listos para copiar: primer contacto, seguimiento, cierre, recordatorio de inscripción, post-resultado y referidos.
A7: Presupuesto | B7: Inversión en anuncios por campaña y costo por alumno inscrito cuando cargues los resultados reales.
A8: Medición | B8: Cada lead entra al SIG con su código de campaña (SPRINT-PUCP, etc.). El Dashboard del SIG muestra leads, inscritos y ventas por campaña.
A9: Ojo | B9: Las fechas de PUCP Talento (~14/02) y ULIMA egresados (~07/03) no son oficiales todavía: revisa a inicios de noviembre y de enero.

Sheet Campanas
A1: Código (SIG) | B1: Campaña | C1: Universidad | D1: Fecha examen | E1: Cierre inscripción | F1: Inicio | G1: Fin | H1: Público | I1: Oferta y precios | J1: Gancho | K1: Canales | L1: Ads S/ por día | M1: Días de ads | N1: Presupuesto ads (S/) | O1: Meta leads | P1: Meta inscritos
A2: SPRINT-ULIMA | B2: Sprint ULIMA | C2: ULIMA | D2: 46341 | E2: 46332 | F2: 46308 | G2: 46341 | H2: 5.° de secundaria que dará el Examen de Escolares ULIMA | I2: Pack 12 horas (12 h) S/ 540 · Programa mensual 24 horas (24 h) S/ 960 | J2: Clase diagnóstica gratis de 45 min + plan de 4 semanas hasta el 15/11 | K2: IG Reels, historias, WhatsApp, web | L2: 20 | M2: 21 | N2: =L2*M2 | O2: 40 | P2: 5
A3: SPRINT-PUCP | B3: Sprint Primera Opción PUCP | C3: PUCP | D3: 46355 | F3: 46309 | G3: 46355 | H3: 5.° de secundaria que dará La Primera Opción PUCP (y ARS 3.ª convocatoria) | I3: Pack 12 horas (12 h) S/ 540 · Programa mensual 24 horas (24 h) S/ 960 | J3: Simulacro diagnóstico gratis tipo PUCP con solucionario + clase diagnóstica de 45 min | K3: IG, FB, grupos de padres, WhatsApp, web | L3: 25 | M3: 28 | N3: =L3*M3 | O3: 60 | P3: 8
A4: REFUERZO-CEPU | B4: Refuerzo CEPU Cayetano | C4: UPCH | D4: 46355 | F4: 46315 | G4: 46355 | H4: Alumnos de CEPU II (Pre Cayetano) antes de su 3.er examen | I4: Hora suelta (1 h) S/ 50 · Grupo 2-3 alumnos (por alumno) (1 h) S/ 35 | J4: Tutoría por curso (Biología, Química, RM) en hora suelta o en grupo de 2-3 | K4: IG, referidos, WhatsApp | L4: 10 | M4: 14 | N4: =L4*M4 | O4: 15 | P4: 3
A5: MEDICINA-UPCH | B5: Ciclo Medicina Cayetano | C5: UPCH | D5: 46404 | E5: 46398 | F5: 46342 | G5: 46404 | H5: 5.° de secundaria y egresados que postulan a Medicina UPCH | I5: Programa mensual 24 horas (24 h) S/ 960 | J5: Webinar gratis 'Medicina UPCH en 8 semanas' + simulacro semanal | K5: IG Ads segmentado, FB, web, WhatsApp | L5: 25 | M5: 35 | N5: =L5*M5 | O5: 40 | P5: 6
A6: VERANO-PUCP | B6: Ciclo Verano Talento PUCP | C6: PUCP | D6: 46432 | F6: 46357 | G6: 46432 | H6: Egresados y quienes no ingresaron el 29/11 (Evaluación del Talento, fecha por confirmar) | I6: Programa mensual 24 horas (24 h) S/ 960 · Grupo 2-3 alumnos (por alumno) (1 h) S/ 35 | J6: 'Segunda oportunidad en febrero': diagnóstico gratis + ciclo de verano | K6: IG Ads, WhatsApp a leads no ingresantes | L6: 20 | M6: 30 | N6: =L6*M6 | O6: 50 | P6: 8
A7: VERANO-ULIMA | B7: Ciclo Verano ULIMA egresados | C7: ULIMA | D7: 46453 | F7: 46357 | G7: 46453 | H7: Egresados que darán el examen ULIMA 2027-1B (fecha no oficial) | I7: Programa mensual 24 horas (24 h) S/ 960 · Pack 12 horas (12 h) S/ 540 | J7: Simulacro diagnóstico + ciclo de verano | K7: IG, FB, WhatsApp | L7: 15 | M7: 25 | N7: =L7*M7 | O7: 30 | P7: 5
A8: CACHIMBOS | B8: Tutoría Cachimbos | C8: Universitario | D8: 46475 | F8: 46357 | G8: 46507 | H8: Ingresantes 2027-1 de PUCP, ULIMA, UPC y UPCH (Cálculo, Física, Química, Estadística) | I8: Práctica (4 h) S/ 220 · Medio ciclo (16 h) S/ 760 · Ciclo completo (32 h) S/ 1,440 · Grupo 2-3 alumnos (por alumno) (1 h) S/ 40 | J8: Lista de espera en diciembre; paquetes por curso desde marzo | K8: IG, grupos de ingresantes, referidos | L8: 15 | M8: 30 | N8: =L8*M8 | O8: 40 | P8: 10
A9: REFERIDOS | B9: Trae a tu tripulación | C9: Todas | F9: 46356 | G9: 46507 | H9: Alumnos y ex alumnos de ASTROS | I9: — | J9: 1 hora gratis por cada referido que compra un paquete (política de precios) | K9: WhatsApp, IG | L9: 0 | M9: 0 | N9: =L9*M9 | O9: 20 | P9: 5
A10: ORGANICO | B10: Contenido de marca | C10: Todas | F10: 46308 | G10: 46507 | H10: Comunidad de @1.masesores | I10: — | J10: Frases ASTROS, tips de estudio, testimonios | K10: IG, FB, TikTok | L10: 0 | M10: 0 | N10: =L10*M10 | O10: 0 | P10: 0

Sheet Calendario
A1: Semana (lunes) | B1: Día | C1: Fecha | D1: Campaña | E1: Formato | F1: Fase | G1: Idea / texto sugerido | H1: Llamado a la acción | I1: Estado | J1: Notas
A2: 46307 | B2: mié | C2: 46309 | D2: SPRINT-PUCP | E2: Carrusel | F2: Lanzamiento | G2: Carrusel: 'Cómo es La Primera Opción PUCP': áreas que evalúa y cómo prepararte en 6 semanas. | H2: Escribe 'DIAGNÓSTICO' al 902 155 458 | I2: Pendiente
A3: 46307 | B3: mié | C3: 46309 | D3: SPRINT-ULIMA | E3: Historia | F3: Urgencia | G3: HITO: Rendimiento Académico ULIMA cierra el 16/10: 'Te preparo para la entrevista'. | H3: Escribe 'ULIMA' al 902 155 458 | I3: Pendiente
A4: 46307 | B4: vie | C4: 46311 | D4: SPRINT-ULIMA | E4: Historia | F4: Lanzamiento | G4: Historia con encuesta: '¿Ya sabes en qué área estás más débil para el Examen de Escolares ULIMA?' Sí / No → link a WhatsApp. | H4: Escribe 'DIAGNÓSTICO' al 902 155 458 | I4: Pendiente
A5: 46307 | B5: sáb | C5: 46312 | D5: SPRINT-ULIMA | E5: WhatsApp | F5: Lanzamiento | G5: Difusión: guion 'Primer contacto' adaptado al Examen de Escolares ULIMA. Ofrece el diagnóstico gratis. | H5: Escribe 'DIAGNÓSTICO' al 902 155 458 | I5: Pendiente
A6: 46314 | B6: lun | C6: 46314 | D6: SPRINT-ULIMA | E6: Reel | F6: Lanzamiento | G6: Reel: 'Un día de estudio con ASTROS': clase virtual, pizarra digital y grabación en Drive, rumbo al Examen de Escolares ULIMA. | H6: Escribe 'DIAGNÓSTICO' al 902 155 458 | I6: Pendiente
A7: 46314 | B7: mié | C7: 46316 | D7: SPRINT-PUCP | E7: Carrusel | F7: Lanzamiento | G7: Carrusel: plan semana a semana para La Primera Opción PUCP (qué estudiar cada semana). | H7: Escribe 'DIAGNÓSTICO' al 902 155 458 | I7: Pendiente
A8: 46314 | B8: vie | C8: 46318 | D8: SPRINT-ULIMA | E8: Historia | F8: Lanzamiento | G8: Historia: caja de preguntas '¿Qué tema te da más miedo?' y responder con mini videos. | H8: Escribe 'DIAGNÓSTICO' al 902 155 458 | I8: Pendiente
A9: 46314 | B9: sáb | C9: 46319 | D9: SPRINT-ULIMA | E9: WhatsApp | F9: Lanzamiento | G9: Difusión: guion 'Seguimiento' a quienes preguntaron y no agendaron diagnóstico. | H9: Escribe 'DIAGNÓSTICO' al 902 155 458 | I9: Pendiente
A10: 46321 | B10: lun | C10: 46321 | D10: SPRINT-ULIMA | E10: Reel | F10: Valor | G10: Reel: resolver en 60 segundos una pregunta tipo ULIMA del banco ASTROS. Cerrar con 'quedan 20 días'. | H10: Escribe 'DIAGNÓSTICO' al 902 155 458 | I10: Pendiente
A11: 46321 | B11: mié | C11: 46323 | D11: SPRINT-PUCP | E11: Carrusel | F11: Lanzamiento | G11: Carrusel: 'Academia grande vs. tutoría personalizada' para La Primera Opción PUCP: horarios, atención y avance medible. | H11: Escribe 'DIAGNÓSTICO' al 902 155 458 | I11: Pendiente
A12: 46321 | B12: vie | C12: 46325 | D12: SPRINT-ULIMA | E12: Historia | F12: Valor | G12: Historia: reto diario de 1 pregunta del banco con respuesta al día siguiente. | H12: Escribe 'DIAGNÓSTICO' al 902 155 458 | I12: Pendiente
A13: 46321 | B13: sáb | C13: 46326 | D13: SPRINT-ULIMA | E13: WhatsApp | F13: Valor | G13: Difusión: guion 'Seguimiento' a leads que no se inscribieron + envío de mini simulacro PDF. | H13: Escribe 'DIAGNÓSTICO' al 902 155 458 | I13: Pendiente
... A122: 46503 | B122: sáb | C122: 46508 | D122: REFERIDOS | E122: WhatsApp | F122: Siempre | G122: Difusión: guion 'Referidos' a alumnos y ex alumnos. | H122: Seguir a @1.masesores | I122: Pendiente

Sheet WhatsApp
A1: Guion | B1: Cuándo usarlo | C1: Texto (copia y pega, cambia lo que está entre [ ])
A2: Primer contacto | B2: Alguien escribe por primera vez | C2: ¡Hola [nombre]! 👋 Soy Martini de ASTROS Maestros Asesores. Gracias por escribirnos. ¿A qué universidad postulas y cuándo es tu examen? Te ofrezco una clase diagnóstica GRATIS de 45 minutos: vemos qué temas dominas, cuáles te faltan y armamos tu plan semana a semana. ¿Qué día te acomoda?
A3: Después del diagnóstico | B3: El mismo día del diagnóstico | C3: ¡Gracias por la clase de hoy, [nombre]! 🚀 Te resumo: estás fuerte en [tema] y conviene reforzar [tema 1] y [tema 2]. Para llegar listo(a) a [examen] el [fecha], te recomiendo [producto] ([horas] h, [precio]). Puedes pagar por Yape, Plin o transferencia. ¿Te reservo tus horarios?
A4: Seguimiento (2-3 días) | B4: No respondió a la propuesta | C4: Hola [nombre], ¿pudiste revisar el plan? Te dejo un mini simulacro tipo [universidad] con solucionario para que practiques 📄. Si te animas, esta semana aún tengo horarios [días].
A5: Cierre | B5: Aceptó la propuesta | C5: ¡Excelente, [nombre]! 🎉 Para confirmar tu cupo, el pago es de [monto] por Yape/Plin o transferencia. Envíame el comprobante por aquí y te mando tu horario y el acceso a tu carpeta de clases grabadas.
A6: Recordatorio de inscripción | B6: Una semana antes del cierre oficial | C6: ⏰ [nombre], la inscripción para [examen] cierra el [fecha y hora]. ¿Ya te inscribiste? Si necesitas ayuda con el proceso, avísame.
A7: Simulacro final | B7: 1-2 semanas antes del examen | C7: Hola [nombre], este [día] hacemos el simulacro final tipo [universidad], cronometrado y con corrección personalizada. ¿Te separo un cupo?
A8: Post-resultado: ingresó | B8: Día de resultados | C8: ¡FELICITACIONES, [nombre]! 🎓🚀 Lo lograste. ¿Me das permiso para compartir tu logro en nuestras redes? Y si tienes amigos que postulan, por cada uno que se inscriba te regalo 1 hora de tutoría para tu primer ciclo.
A9: Post-resultado: no ingresó | B9: Día de resultados | C9: [nombre], sé que no es la noticia que esperabas. Lo que preparaste no se pierde: el próximo proceso es [fecha]. Te propongo revisar juntos tu examen y armar un plan de verano. ¿Conversamos esta semana?
A10: Referidos | B10: Alumnos actuales y ex alumnos | C10: Hola [nombre] 👋 ¿Conoces a alguien que postule a PUCP, ULIMA, UPC o Cayetano, o que necesite ayuda en la universidad? Por cada amigo que se inscriba en un paquete, te regalo 1 hora de clase. ¡Gracias por ser parte de la tripulación ASTROS!

Sheet Presupuesto
A1: Código | B1: Presupuesto ads (S/) | C1: Meta inscritos | D1: Costo meta por inscrito (S/) | E1: Gasto real (S/) | F1: Inscritos reales (del SIG) | G1: Costo real por inscrito (S/)
A2: =Campanas!A2 | B2: =Campanas!N2 | C2: =Campanas!P2 | D2: =IFERROR(B2/C2,"") | G2: =IFERROR(E2/F2,"")
A3: =Campanas!A3 | B3: =Campanas!N3 | C3: =Campanas!P3 | D3: =IFERROR(B3/C3,"") | G3: =IFERROR(E3/F3,"")
A4: =Campanas!A4 | B4: =Campanas!N4 | C4: =Campanas!P4 | D4: =IFERROR(B4/C4,"") | G4: =IFERROR(E4/F4,"")
A5: =Campanas!A5 | B5: =Campanas!N5 | C5: =Campanas!P5 | D5: =IFERROR(B5/C5,"") | G5: =IFERROR(E5/F5,"")
A6: =Campanas!A6 | B6: =Campanas!N6 | C6: =Campanas!P6 | D6: =IFERROR(B6/C6,"") | G6: =IFERROR(E6/F6,"")
A7: =Campanas!A7 | B7: =Campanas!N7 | C7: =Campanas!P7 | D7: =IFERROR(B7/C7,"") | G7: =IFERROR(E7/F7,"")
A8: =Campanas!A8 | B8: =Campanas!N8 | C8: =Campanas!P8 | D8: =IFERROR(B8/C8,"") | G8: =IFERROR(E8/F8,"")
A9: =Campanas!A9 | B9: =Campanas!N9 | C9: =Campanas!P9 | D9: =IFERROR(B9/C9,"") | G9: =IFERROR(E9/F9,"")
A10: =Campanas!A10 | B10: =Campanas!N10 | C10: =Campanas!P10 | D10: =IFERROR(B10/C10,"") | G10: =IFERROR(E10/F10,"")
A11: TOTAL | B11: =SUM(B2:B10) | C11: =SUM(C2:C10) | D11: =IFERROR(B11/C11,"") | E11: =SUM(E2:E10) | F11: =SUM(F2:F10) | G11: =IFERROR(E11/F11,"")
A13: Anuncios en Meta (IG/FB): segmenta Lima, 16-19 años y padres 38-55, intereses 'admisión universitaria' y la universidad. Empieza con el mínimo diario y sube solo en los anuncios con más mensajes por sol.
